gjob/__init__.py
gjob-2025.0.0.dist-info/WHEEL
gjob-2025.0.0.dist-info/METADATA
gjob-2025.0.0.dist-info/RECORD
