Metadata-Version: 2.3
Name: gjob
Version: 2025.0.0
Summary: Process Google Careers job alert emails
Author: Blake Naccarato
Author-email: Blake Naccarato <blake.naccarato@gmail.com>
License: MIT License
Classifier: License :: OSI Approved :: MIT License
Classifier: Programming Language :: Python :: 3.11
Classifier: Programming Language :: Python :: 3.12
Requires-Python: >=3.11
Project-URL: Changes, https://blakeNaccarato.github.io/gjob/changelog.html
Project-URL: Docs, https://blakeNaccarato.github.io/gjob
Project-URL: Home, https://github.com/blakeNaccarato/gjob
Project-URL: Tracker, https://github.com/blakeNaccarato/gjob/issues
